LICENSE.md
wiki_fetch/__init__.py
wiki_fetch/__main__.py
wiki_fetch/driver.py
wiki_fetch/generic.py
wiki_fetch/parser.py
wiki_fetch/parts.py
wiki_fetch/stuff.py
wiki_fetch-0.1.1.dist-info/LICENSE.md
wiki_fetch-0.1.1.dist-info/WHEEL
wiki_fetch-0.1.1.dist-info/METADATA
wiki_fetch-0.1.1.dist-info/entry_points.txt
wiki_fetch-0.1.1.dist-info/RECORD
