Metadata-Version: 2.1
Name: wiki-fetch
Version: 0.1.1
Summary: Parser for Wikipedia.org
Home-page: https://github.com/d3z-the-dev/wiki-fetch
License: Apache-2.0
Keywords: parser,wiki,wikipedia,web scraping
Author: d3z
Author-email: d3z.the.dev@gmail.com
Requires-Python: >=3.10,<4.0
Classifier: Development Status :: 3 - Alpha
Classifier: Environment :: Console
Classifier: License :: OSI Approved :: Apache Software License
Classifier: Natural Language :: English
Classifier: Operating System :: OS Independent
Classifier: Programming Language :: Python :: 3
Classifier: Programming Language :: Python :: 3.10
Classifier: Programming Language :: Python :: 3.11
Classifier: Programming Language :: Python :: 3 :: Only
Classifier: Programming Language :: Python :: 3.10
Classifier: Programming Language :: Python :: 3.9
Classifier: Topic :: Internet :: WWW/HTTP :: Dynamic Content :: Wiki
Classifier: Typing :: Typed
Requires-Dist: bs4 (>=0.0.1,<0.0.2)
Project-URL: Repository, https://github.com/d3z-the-dev/wiki-fetch
